maid_sweeper/__main__.py
maid_sweeper/context.py
maid_sweeper/dispatcher.py
maid_sweeper/maid.py
maid_sweeper/patterns.py
maid_sweeper-0.6.96.dist-info/LICENSE
maid_sweeper-0.6.96.dist-info/METADATA
maid_sweeper-0.6.96.dist-info/WHEEL
maid_sweeper-0.6.96.dist-info/entry_points.txt
maid_sweeper-0.6.96.dist-info/top_level.txt
maid_sweeper-0.6.96.dist-info/RECORD
