Metadata-Version: 2.1
Name: maid-sweeper
Version: 0.6.96
Summary: A maid that sweeps your files
Author-email: noirgif <nomaru@outlook.com>
Project-URL: Homepage, https://github.com/noirgif/maid-sweeper
Project-URL: Bug Tracker, https://github.com/noirgif/maid-sweeper/issues
Classifier: Programming Language :: Python :: 3
Classifier: License :: OSI Approved :: MIT License
Classifier: Operating System :: OS Independent
Requires-Python: >=3.10
License-File: LICENSE
Requires-Dist: nest-asyncio
Requires-Dist: motor
Requires-Dist: certifi
